{"P9": {"labels": ["Windows", "\u5c0f\u7c73"], "postTitle": "\u4fee\u590d\u81ea\u88c5\u5c0f\u7c73\u7535\u8111\u7ba1\u5bb6\u6444\u50cf\u5934\u5f39\u7a97\u95ee\u9898", "postUrl": "post/xiu-fu-zi-zhuang-xiao-mi-dian-nao-guan-jia-she-xiang-tou-dan-chuang-wen-ti.html", "createdDate": "2026-01-22", "dateLabelColor": "#1f883d"}, "P8": {"labels": ["bug", "Windows"], "postTitle": "Windows 11\u7684\u79fb\u52a8\u70ed\u70b9\u663e\u793a\u65e0\u6cd5\u542f\u52a8\u600e\u4e48\u529e\uff1f", "postUrl": "post/Windows%2011-de-yi-dong-re-dian-xian-shi-wu-fa-qi-dong-zen-me-ban-%EF%BC%9F.html", "createdDate": "2026-01-13", "dateLabelColor": "#1f883d"}, "P7": {"labels": ["\u968f\u7b14", "\u9605\u8bfb\u611f\u609f"], "postTitle": "\u6211\u4eec\u4e0a\u7f51\u90fd\u5728\u770b\u4e9b\u4ec0\u4e48\uff1f", "postUrl": "post/wo-men-shang-wang-du-zai-kan-xie-shen-me-%EF%BC%9F.html", "createdDate": "2026-01-03", "dateLabelColor": "#1f883d"}, "P5": {"labels": ["\u968f\u7b14", "\u9605\u8bfb\u611f\u609f"], "postTitle": "\u8c01\u52a8\u4e86\u6211\u7684\u5976\u916a", "postUrl": "post/shui-dong-le-wo-de-nai-lao.html", "createdDate": "2022-04-25", "dateLabelColor": "#1f883d"}, "labelColorDict": {"about": "#22d683", "bug": "#d73a4a", "documentation": "#0075ca", "duplicate": "#cfd3d7", "enhancement": "#a2eeef", "good first issue": "#7057ff", "help wanted": "#008672", "invalid": "#e4e669", "link": "#116e6c", "question": "#d876e3", "Windows": "#6f99b0", "wontfix": "#ffffff", "\u5c0f\u7c73": "#a6772e", "\u9605\u8bfb\u611f\u609f": "#b6823b", "\u968f\u7b14": "#ea5b85"}}